ywatch/__init__.py
ywatch/checklink.py
ywatch/dataprocess.py
ywatch/menu.py
ywatch/userInputs.py
ywatch/yw.py
ywatch-0.6.3.dist-info/LICENSE
ywatch-0.6.3.dist-info/METADATA
ywatch-0.6.3.dist-info/WHEEL
ywatch-0.6.3.dist-info/entry_points.txt
ywatch-0.6.3.dist-info/top_level.txt
ywatch-0.6.3.dist-info/RECORD
